abx_plugin_sonic_search/__init__.py
abx_plugin_sonic_search/binaries.py
abx_plugin_sonic_search/config.py
abx_plugin_sonic_search/searchbackend.py
abx_plugin_sonic_search-2024.10.28.dist-info/METADATA
abx_plugin_sonic_search-2024.10.28.dist-info/WHEEL
abx_plugin_sonic_search-2024.10.28.dist-info/entry_points.txt
abx_plugin_sonic_search-2024.10.28.dist-info/RECORD
